.gitignore
CHANGES.txt
README.rst
buildout.cfg
setup.py
hostout/__init__.py
hostout.supervisor.egg-info/PKG-INFO
hostout.supervisor.egg-info/SOURCES.txt
hostout.supervisor.egg-info/dependency_links.txt
hostout.supervisor.egg-info/entry_points.txt
hostout.supervisor.egg-info/namespace_packages.txt
hostout.supervisor.egg-info/not-zip-safe
hostout.supervisor.egg-info/requires.txt
hostout.supervisor.egg-info/top_level.txt
hostout/supervisor/__init__.py
hostout/supervisor/fabfile.py
hostout/supervisor/tests.py