Metadata-Version: 1.0
Name: hostout.supervisor
Version: 1.0a5
Summary: Plugin for collective.hostout that starts and stops supervisor
Home-page: https://svn.plone.org/svn/collective/hostout.supervisor
Author: Dylan Jay
Author-email: software@pretaweb.com
License: GPL
Keywords: buildout,fabric,deploy,deployment,server,plone,django,host,hosting
Platform: UNKNOWN
